Metadata-Version: 2.1
Name: s3transfer
Version: 0.11.1
Summary: An Amazon S3 Transfer Manager
Home-page: https://github.com/boto/s3transfer
Author: Amazon Web Services
Author-email: kyknapp1@gmail.com
License: Apache License 2.0
Classifier: Development Status :: 3 - Alpha
Classifier: Intended Audience :: Developers
Classifier: Natural Language :: English
Classifier: License :: OSI Approved :: Apache Software License
Classifier: Programming Language :: Python
Classifier: Programming Language :: Python :: 3
Classifier: Programming Language :: Python :: 3 :: Only
Classifier: Programming Language :: Python :: 3.8
Classifier: Programming Language :: Python :: 3.9
Classifier: Programming Language :: Python :: 3.10
Classifier: Programming Language :: Python :: 3.11
Classifier: Programming Language :: Python :: 3.12
Classifier: Programming Language :: Python :: 3.13
Requires-Python: >= 3.8
License-File: LICENSE.txt
License-File: NOTICE.txt
Requires-Dist: botocore<2.0a.0,>=1.36.0
Provides-Extra: crt
Requires-Dist: botocore[crt]<2.0a.0,>=1.36.0; extra == "crt"
